textual_markdown/__init__.py
textual_markdown/__main__.py
textual_markdown/browser_app.py
textual_markdown/navigator.py
textual_markdown/widgets.py
textual_markdown-0.1.1.dist-info/LICENSE
textual_markdown-0.1.1.dist-info/WHEEL
textual_markdown-0.1.1.dist-info/METADATA
textual_markdown-0.1.1.dist-info/RECORD
