Metadata-Version: 2.1
Name: textual-markdown
Version: 0.1.1
Summary: Markdown viewer widgets for Textual
License: MIT
Author: Will McGugan
Author-email: willmcgugan@gmail.com
Requires-Python: >=3.7,<4.0
Classifier: License :: OSI Approved :: MIT License
Classifier: Programming Language :: Python :: 3
Classifier: Programming Language :: Python :: 3.7
Classifier: Programming Language :: Python :: 3.8
Classifier: Programming Language :: Python :: 3.9
Classifier: Programming Language :: Python :: 3.10
Classifier: Programming Language :: Python :: 3.11
Requires-Dist: markdown-it-py[linkify,plugins] (>=2.1.0,<3.0.0)
Requires-Dist: textual[dev] (>=0.7.0,<0.8.0)
